gridgulp/__init__.py
gridgulp/config.py
gridgulp/detection.py
gridgulp/gridgulp.py
gridgulp/py.typed
gridgulp/core/__init__.py
gridgulp/core/configurable_constants.py
gridgulp/core/constants.py
gridgulp/core/exceptions.py
gridgulp/core/types.py
gridgulp/detectors/__init__.py
gridgulp/detectors/box_table_detector.py
gridgulp/detectors/excel_metadata_extractor.py
gridgulp/detectors/format_analyzer.py
gridgulp/detectors/island_detector.py
gridgulp/detectors/merged_cell_analyzer.py
gridgulp/detectors/multi_header_detector.py
gridgulp/detectors/simple_case_detector.py
gridgulp/detectors/structured_text_detector.py
gridgulp/extractors/__init__.py
gridgulp/extractors/dataframe_extractor.py
gridgulp/models/__init__.py
gridgulp/models/detection_result.py
gridgulp/models/extraction_result.py
gridgulp/models/file_data.py
gridgulp/models/file_info.py
gridgulp/models/sheet_data.py
gridgulp/models/table.py
gridgulp/readers/__init__.py
gridgulp/readers/base_reader.py
gridgulp/readers/convenience.py
gridgulp/readers/csv_reader.py
gridgulp/readers/excel_reader.py
gridgulp/readers/factory.py
gridgulp/readers/reader_adapter.py
gridgulp/readers/text_reader.py
gridgulp/utils/__init__.py
gridgulp/utils/excel_utils.py
gridgulp/utils/file_magic.py
gridgulp/utils/logging_context.py
gridgulp/utils/visualization.py
gridgulp-0.3.4.dist-info/METADATA
gridgulp-0.3.4.dist-info/WHEEL
gridgulp-0.3.4.dist-info/entry_points.txt
gridgulp-0.3.4.dist-info/licenses/LICENSE
gridgulp-0.3.4.dist-info/licenses/NOTICE
gridgulp-0.3.4.dist-info/RECORD
