Metadata-Version: 2.4
Name: gridgulp
Version: 0.3.4
Summary: Simplified intelligent spreadsheet ingestion framework with automatic table detection
Project-URL: Homepage, https://github.com/Ganymede-Bio/gridgulp
Project-URL: Repository, https://github.com/Ganymede-Bio/gridgulp
Project-URL: Issues, https://github.com/Ganymede-Bio/gridgulp/issues
Author: GridGulp Contributors
License: MIT
License-File: LICENSE
License-File: NOTICE
Keywords: csv,data-extraction,excel,spreadsheet,table-detection
Classifier: Development Status :: 3 - Alpha
Classifier: Intended Audience :: Developers
Classifier: License :: OSI Approved :: MIT License
Classifier: Programming Language :: Python :: 3
Classifier: Programming Language :: Python :: 3.10
Classifier: Programming Language :: Python :: 3.11
Classifier: Programming Language :: Python :: 3.12
Classifier: Programming Language :: Python :: 3.13
Classifier: Topic :: Office/Business :: Financial :: Spreadsheet
Classifier: Topic :: Software Development :: Libraries :: Python Modules
Requires-Python: >=3.10
Requires-Dist: aiofiles
Requires-Dist: chardet
Requires-Dist: filetype>=1.2.0
Requires-Dist: magika
Requires-Dist: numpy
Requires-Dist: olefile
Requires-Dist: openpyxl
Requires-Dist: pandas>=2.0.0
Requires-Dist: polars
Requires-Dist: pydantic<3.0,>=2.0
Requires-Dist: python-magic
Requires-Dist: rich
Requires-Dist: scipy>=1.11.0
Requires-Dist: xlrd
Provides-Extra: dev
Requires-Dist: ipykernel>=6.25.0; extra == 'dev'
Requires-Dist: mypy>=1.5.0; extra == 'dev'
Requires-Dist: pandas-stubs>=2.0.0; extra == 'dev'
Requires-Dist: pre-commit>=3.3.0; extra == 'dev'
Requires-Dist: psutil>=7.0.0; extra == 'dev'
Requires-Dist: pytest-asyncio>=0.21.0; extra == 'dev'
Requires-Dist: pytest-cov>=4.1.0; extra == 'dev'
Requires-Dist: pytest-xdist>=3.8.0; extra == 'dev'
Requires-Dist: pytest>=8.4.0; extra == 'dev'
Requires-Dist: ruff>=0.12.0; extra == 'dev'
Requires-Dist: types-aiofiles; extra == 'dev'
Provides-Extra: docs
Requires-Dist: mkdocs-gen-files>=0.5.0; extra == 'docs'
Requires-Dist: mkdocs-literate-nav>=0.6.0; extra == 'docs'
Requires-Dist: mkdocs-material>=9.0.0; extra == 'docs'
Requires-Dist: mkdocs-section-index>=0.3.0; extra == 'docs'
Requires-Dist: mkdocs>=1.5.0; extra == 'docs'
Requires-Dist: mkdocstrings[python]>=0.24.0; extra == 'docs'
Requires-Dist: pymdown-extensions>=10.0; extra == 'docs'
